HISTORY.rst
MANIFEST.in
README.rst
requirements.txt
setup.py
txshark/__init__.py
txshark/packet.py
txshark/protocol.py
txshark/service.py
txshark.egg-info/PKG-INFO
txshark.egg-info/SOURCES.txt
txshark.egg-info/dependency_links.txt
txshark.egg-info/requires.txt
txshark.egg-info/top_level.txt
txshark/test/__init__.py
txshark/test/test_service.py