Metadata-Version: 1.1
Name: txshark
Version: 0.1.0
Summary: Python/Twisted wrapper for tshark
Home-page: https://github.com/beenje/txshark
Author: Benjamin Bertrand
Author-email: beenje@gmail.com
License: MIT
Keywords: wireshark packet parsing twisted
Platform: UNKNOWN
Classifier: Development Status :: 4 - Beta
Classifier: Topic :: Software Development
Classifier: License :: OSI Approved :: MIT License
Classifier: Intended Audience :: Developers
Classifier: Programming Language :: Python
